hdcproto/__init__.py
hdcproto/common.py
hdcproto/demo/__init__.py
hdcproto/demo/generic/__init__.py
hdcproto/demo/generic/showcase_echo.py
hdcproto/demo/generic/showcase_introspection.py
hdcproto/demo/generic/showcase_logging.py
hdcproto/demo/minimal/__init__.py
hdcproto/demo/minimal/minimal_proxy.py
hdcproto/demo/minimal/showcase_minimal.py
hdcproto/demo/minimal/showcase_reset.py
hdcproto/host/__init__.py
hdcproto/host/proxy.py
hdcproto/host/router.py
hdcproto/test/__init__.py
hdcproto/test/test_Packetizer.py
hdcproto/test/test_SerialTransport.py
hdcproto/test/test_host_proxy.py
hdcproto/test/test_payload_parser.py
hdcproto/transport/__init__.py
hdcproto/transport/base.py
hdcproto/transport/packetizer.py
hdcproto/transport/serialport.py
hdcproto-0.0.8.dist-info/METADATA
hdcproto-0.0.8.dist-info/WHEEL
hdcproto-0.0.8.dist-info/licenses/LICENSE.txt
hdcproto-0.0.8.dist-info/RECORD
