Metadata-Version: 2.1
Name: hdcproto
Version: 0.0.8
Summary: Host Device Communication protocol
Project-URL: Documentation, https://github.com/kiksotik/hdc#readme
Project-URL: Issues, https://github.com/kiksotik/hdc/issues
Project-URL: Source, https://github.com/kiksotik/hdc
Author-email: "Axel T. J. Rohde" <kiksotik@gmail.com>
License-File: LICENSE.txt
Classifier: Development Status :: 2 - Pre-Alpha
Classifier: License :: OSI Approved :: MIT License
Classifier: Programming Language :: Python
Classifier: Programming Language :: Python :: 3.7
Classifier: Programming Language :: Python :: 3.8
Classifier: Programming Language :: Python :: 3.9
Classifier: Programming Language :: Python :: 3.10
Classifier: Programming Language :: Python :: 3.11
Classifier: Programming Language :: Python :: Implementation :: CPython
Classifier: Programming Language :: Python :: Implementation :: PyPy
Requires-Python: >=3.7
Requires-Dist: pyserial~=3.5
Requires-Dist: semver~=2.13.0
